setup.py
bayes/__init__.py
bayes/bayesNets.py
bayes/sample_input_txt.py
bayes_nets_sample-1.5.dist-info/METADATA
bayes_nets_sample-1.5.dist-info/WHEEL
bayes_nets_sample-1.5.dist-info/licenses/LICENSE
bayes_nets_sample-1.5.dist-info/RECORD
